wowool/apps/filter/__init__.py
wowool/apps/filter/config.py
wowool/apps/grep/__init__.py
wowool/apps/grep/config.py
wowool/apps/language_identifier/__init__.py
wowool/apps/language_identifier/__main__.py
wowool/apps/language_identifier/app_id.py
wowool/apps/language_identifier/argument_parser.py
wowool/apps/language_identifier/config.py
wowool/apps/unit_test/__init__.py
wowool/apps/unit_test/config.py
wowool/apps/workflow/__init__.py
wowool/apps/workflow/config.py
wowool/grep/__init__.py
wowool/grep/app_id.py
wowool/grep/grep.py
wowool/native/afst_cpp.py
wowool/native/woc_cpp.py
wowool/native/wow_cpp.py
wowool/native/core/__init__.py
wowool/native/core/analysis.py
wowool/native/core/app_id.py
wowool/native/core/compiler.py
wowool/native/core/component_info.py
wowool/native/core/domain.py
wowool/native/core/domain_info.py
wowool/native/core/engine.py
wowool/native/core/filter.py
wowool/native/core/language.py
wowool/native/core/language_identifier.py
wowool/native/core/language_info.py
wowool/native/core/pipeline.py
wowool/native/core/pipeline_exceptions.py
wowool/native/core/pipeline_info.py
wowool/native/core/pipeline_resolver.py
wowool/native/core/sdk_exceptions.py
wowool/native/core/version.py
wowool/native/create_locale_language/__main__.py
wowool/native/woc/__main__.py
wowool/native/woc/argument_parser.py
wowool/native/woc/command/__init__.py
wowool/native/woc/command/compile.py
wowool/native/woc/command/create.py
wowool/native/woc/command/project.py
wowool/native/woc/command/version.py
wowool/native/wow/__main__.py
wowool/native/wow/argument_parser.py
wowool/native/wow_copy/__main__.py
wowool/native/wow_copy/argument_parser.py
wowool/plugin/__init__.py
wowool/plugin/date_parser.py
wowool/sdk/__init__.py
wowool/tools/grep/__main__.py
wowool/tools/grep/argument_parser.py
wowool/typing/typing.py
wowool/workflow/__init__.py
wowool/workflow/app_id.py
wowool/workflow/workflow.py
wowool/workflow/action/__init__.py
wowool/workflow/action/base.py
wowool_sdk-3.5.7.dist-info/METADATA
wowool_sdk-3.5.7.dist-info/WHEEL
wowool_sdk-3.5.7.dist-info/entry_points.txt
wowool_sdk-3.5.7.dist-info/top_level.txt
wowool_sdk-3.5.7.dist-info/RECORD
