Metadata-Version: 2.4
Name: wowool-sdk
Version: 3.5.7
Summary: Wowool SDK
Home-page: https://www.wowool.com/
Author: Wowool
Author-email: info@wowool.com
Requires-Python: >=3.11
Requires-Dist: wowool-common<3.7.0,>=3.6.0
Requires-Dist: wowool-sdk-cpp<3.6.0,>=3.5.0
Requires-Dist: wowool-lid
Requires-Dist: wowool-generic
Requires-Dist: dateparser
Requires-Dist: jsonschema
Requires-Dist: unidecode
Requires-Dist: tabulate
Requires-Dist: jinja2
Requires-Dist: jsonpath_ng
Requires-Dist: rich
Requires-Dist: tabulate
Dynamic: author
Dynamic: author-email
Dynamic: description
Dynamic: description-content-type
Dynamic: home-page
Dynamic: requires-dist
Dynamic: requires-python
Dynamic: summary
